pypkgconf-2.1.1.1.dist-info/METADATA
pypkgconf-2.1.1.1.dist-info/WHEEL
pypkgconf-2.1.1.1.dist-info/LICENSE.txt
pypkgconf-2.1.1.1.data/scripts/pkgconf.exe
pypkgconf/_libpkgconf.pyd
pypkgconf/version.py
pypkgconf/__init__.py
pypkgconf/callbacks.py
pypkgconf/clilike.py
pypkgconf/constants.py
pypkgconf/logger.py
pypkgconf/util.py
pypkgconf-2.1.1.1.dist-info/RECORD
