Metadata-Version: 2.1
Name: pypkgconf
Version: 2.1.1.1
Summary: Python bindings to libpkgconf
Author-Email: Charles Brunet <charles.brunet@optelgroup.com>
License:                                  Apache License
Project-URL: Source, https://gitlab.com/optelgroup-public/pypkgconf
Project-URL: Tracker, https://gitlab.com/optelgroup-public/pypkgconf/-/issues
Requires-Python: >=3.7
Requires-Dist: cffi
Requires-Dist: pytest; extra == "test"
Provides-Extra: test
